vairo/__init__.py
vairo/helper.txt
vairo/run_vairo.py
vairo/ALEPH/__init__.py
vairo/ALEPH/setup.py
vairo/ALEPH/aleph/__init__.py
vairo/ALEPH/aleph/core/ALEPH.py
vairo/ALEPH/aleph/core/Bioinformatics.py
vairo/ALEPH/aleph/core/Grid.py
vairo/ALEPH/aleph/core/SystemUtility.py
vairo/ALEPH/aleph/core/__init__.py
vairo/ALEPH/aleph/core/managerSSH.py
vairo/app/README.md
vairo/app/__init__.py
vairo/app/app.py
vairo/app/static/components/__init__.py
vairo/app/static/components/accordion.js
vairo/app/static/components/feature.js
vairo/app/static/components/library.js
vairo/app/static/components/modfeatures.js
vairo/app/static/components/sequence.js
vairo/app/static/components/summary.js
vairo/app/static/components/template.js
vairo/app/static/css/__init__.py
vairo/app/static/css/all.css
vairo/app/static/css/bootstrap.css
vairo/app/static/css/styles.css
vairo/app/static/images/__init__.py
vairo/app/static/images/vairo_scheme.png
vairo/app/static/js/.DS_Store
vairo/app/static/js/__init__.py
vairo/app/static/js/bootstrap.js
vairo/app/static/js/input.js
vairo/app/static/js/jquery.min.js
vairo/app/static/js/main.js
vairo/app/static/js/ngl.js
vairo/app/static/js/output.js
vairo/app/static/js/parameterization.js
vairo/app/static/js/plotly.js
vairo/app/static/webfonts/__init__.py
vairo/app/static/webfonts/fa-brands-400.ttf
vairo/app/static/webfonts/fa-brands-400.woff2
vairo/app/static/webfonts/fa-regular-400.ttf
vairo/app/static/webfonts/fa-regular-400.woff2
vairo/app/static/webfonts/fa-solid-900.ttf
vairo/app/static/webfonts/fa-solid-900.woff2
vairo/app/static/webfonts/fa-v4compatibility.ttf
vairo/app/static/webfonts/fa-v4compatibility.woff2
vairo/app/templates/__init__.py
vairo/app/templates/footer.html
vairo/app/templates/header.html
vairo/app/templates/index.html
vairo/app/templates/input.html
vairo/app/templates/modfeatures.html
vairo/app/templates/modfeaturesinfo.html
vairo/app/templates/nav.html
vairo/app/templates/output.html
vairo/app/templates/parameterization.html
vairo-1.0.0.dist-info/METADATA
vairo-1.0.0.dist-info/WHEEL
vairo-1.0.0.dist-info/entry_points.txt
vairo-1.0.0.dist-info/top_level.txt
vairo-1.0.0.dist-info/RECORD
