Metadata-Version: 2.1
Name: vairo
Version: 1.0.0
Summary: VAIRO guides predictions towards particular dynamic states selecting the prior information input or analysing the results of the search.
Home-page: http://chango.ibmb.csic.es
Author: Isabel Uson
Author-email: bugs-borges@ibmb.csic.es
Keywords: crystallography macromolecular
Classifier: Operating System :: Unix
Classifier: Development Status :: 5 - Production/Stable
Classifier: Topic :: Scientific/Engineering :: Bio-Informatics
Classifier: License :: OSI Approved :: BSD License
Classifier: Programming Language :: Python :: 3.6
Classifier: Programming Language :: Python :: 3.7
Classifier: Programming Language :: Python :: 3.8
Classifier: Programming Language :: Python :: 3.9
Classifier: Programming Language :: Python :: 3.10
Classifier: Programming Language :: Python :: 3.11
Classifier: Programming Language :: Python :: 3.12
Classifier: Programming Language :: Python :: 3.13
Requires-Python: >=3.6
